Metadata-Version: 1.0
Name: bin-gaussian
Version: 1.0.1
Summary: Gaussian distributions and binomial distributions
Home-page: UNKNOWN
Author: oluwatobi ojo
Author-email: oluwatobiojo453@gmail.com
License: UNKNOWN
Platform: UNKNOWN
